soscipy/__init__.py
soscipy/analyse/__init__.py
soscipy/analyse/dat2csv.py
soscipy/fetch/ASER.py
soscipy/fetch/HighCourt.py
soscipy/fetch/MOSPI.py
soscipy/fetch/NCRB.py
soscipy/fetch/NFHS.py
soscipy/fetch/Supremo.py
soscipy/fetch/WorldBank.py
soscipy/fetch/__init__.py
soscipy/fetch/wb.py
soscipy/plot/__init__.py
soscipy/plot/changeovtime.py
soscipy/plot/correlation.py
soscipy/plot/deviation.py
soscipy/plot/distribution.py
soscipy/plot/flow.py
soscipy/plot/magnitude.py
soscipy/plot/part2whole.py
soscipy/plot/plot.py
soscipy/plot/ranking.py
soscipy/plot/spatial.py
soscipy/process/__init__.py
soscipy/process/combine.py
soscipy/process/dfops.py
soscipy/process/dictops.py
soscipy/process/enrich.py
soscipy/process/listops.py
soscipy/process/rename_pd.py
soscipy/process/xlwriter.py
soscipy/utilities/__init__.py
soscipy/utilities/br.py
soscipy/utilities/paralle.py
soscipy/utilities/progress_bar.py
soscipy/visualise/__init__.py
soscipy/visualise/plot.py
soscipy-0.0.44.dist-info/METADATA
soscipy-0.0.44.dist-info/WHEEL
soscipy-0.0.44.dist-info/top_level.txt
soscipy-0.0.44.dist-info/RECORD
