Metadata-Version: 2.1
Name: soscipy
Version: 0.0.44
Summary: A python library to help do reproducible research in social sciences
Home-page: UNKNOWN
Author: Saurabh Karn
License: MIT
Platform: UNKNOWN
Requires-Dist: bleach (==3.3.0)
Requires-Dist: build (==0.3.1.post1)
Requires-Dist: certifi (==2020.12.5)
Requires-Dist: chardet (==4.0.0)
Requires-Dist: colorama (==0.4.4)
Requires-Dist: docutils (==0.17.1)
Requires-Dist: idna (==2.10)
Requires-Dist: importlib-metadata (==4.0.1)
Requires-Dist: keyring (==23.0.1)
Requires-Dist: packaging (==20.9)
Requires-Dist: pep517 (==0.10.0)
Requires-Dist: pip (==21.0.1)
Requires-Dist: pkginfo (==1.7.0)
Requires-Dist: Pygments (==2.8.1)
Requires-Dist: pyparsing (==2.4.7)
Requires-Dist: readme-renderer (==29.0)
Requires-Dist: requests (==2.25.1)
Requires-Dist: requests-toolbelt (==0.9.1)
Requires-Dist: rfc3986 (==1.4.0)
Requires-Dist: setuptools
Requires-Dist: six (==1.15.0)
Requires-Dist: toml (==0.10.2)
Requires-Dist: tqdm (==4.60.0)
Requires-Dist: twine (==3.4.1)
Requires-Dist: urllib3 (==1.26.4)
Requires-Dist: webencodings (==0.5.1)
Requires-Dist: wheel (==0.36.2)
Requires-Dist: zipp (==3.4.1)
Requires-Dist: pandas
Requires-Dist: bs4
Requires-Dist: selenium
Requires-Dist: webdriver-manager
